LICENSE
README.md
pyproject.toml
setup.cfg
setup.py
examples/altair_example.py
examples/markdown_example.py
examples/plotly_example.py
examples/report_example.py
examples/old/markdown_electron.py
examples/old/markdown_local.py
figurl/__init__.py
figurl/cli.py
figurl/version.py
figurl.egg-info/PKG-INFO
figurl.egg-info/SOURCES.txt
figurl.egg-info/dependency_links.txt
figurl.egg-info/entry_points.txt
figurl.egg-info/requires.txt
figurl.egg-info/top_level.txt
figurl/core/Figure.py
figurl/core/__init__.py
figurl/core/serialize_wrapper.py
figurl/plugins/__init__.py
figurl/plugins/builtin/__init__.py
figurl/plugins/builtin/altair/Altair.py
figurl/plugins/builtin/altair/__init__.py
figurl/plugins/builtin/markdown/Markdown.py
figurl/plugins/builtin/markdown/__init__.py
figurl/plugins/builtin/plotly/Plotly.py
figurl/plugins/builtin/plotly/__init__.py
figurl/plugins/builtin/report/Report.py
figurl/plugins/builtin/report/__init__.py
figurl/preserve/__init__.py
figurl/preserve/preserve.py
figurl/preserve/templates/index.html