Metadata-Version: 2.1
Name: figurl
Version: 0.3.1
Home-page: https://github.com/flatironinstitute/figurl
Author: Jeremy Magland
Author-email: Jeremy Magland <jmagland@flatironinstitute.org>
License: Apache License (2.0)
Project-URL: Homepage, https://github.com/flatironinstitute/figurl
Project-URL: Issues, https://github.com/flatironinstitute/figurl/issues
Classifier: Operating System :: OS Independent
Classifier: Programming Language :: Python :: 3
License-File: LICENSE
Requires-Dist: altair
Requires-Dist: click
Requires-Dist: kachery>=2.0.1
